{ "ColorTest" : { "angleVariance" : 0.0, "duration" : 0.0, "finishColor" : "#ffffff", "finishColorAlpha" : 0.0, "finishColorVariance" : "#000000", "finishColorVarianceAlpha" : 0.0, "finishParticleSize" : 45.0, "finishParticleSizeVariance" : 10.0, "gravity" : "0.0, 0.0", "maxParticles" : 13.0, "maxRadius" : 0.0, "maxRadiusVariance" : 0.0, "minRadius" : 0.0, "minRadiusVariance" : 0.0, "particleLifespan" : 0.9000000000000000222, "particleLifespanVariance" : 0.2000000000000000111, "radialAccelVariance" : 0.0, "radialAcceleration" : 0.0, "rotatePerSecond" : 0.0, "rotatePerSecondVariance" : 0.0, "rotation" : 0.0, "rotationEnd" : 0.0, "rotationEndVariance" : 0.0, "rotationStart" : 0.0, "rotationStartVariance" : 0.0, "sourcePositionVariance" : "0.0, 0.0", "speed" : 211.0, "speedVariance" : 0.0, "startColor" : "#ffffff", "startColorAlpha" : 1.0, "startColorVariance" : "#ffffff", "startColorVarianceAlpha" : 1.0, "startParticleSize" : 7.0, "startParticleSizeVariance" : 2.0, "tangentialAccelVariance" : 0.0, "tangentialAcceleration" : 0.0, "textureFileName" : "arrow.png", "visible" : true, "x" : 0.0, "y" : 0.0 } }